odoo/addons/cms_status_message/CHANGES.rst
odoo/addons/cms_status_message/README.rst
odoo/addons/cms_status_message/__init__.py
odoo/addons/cms_status_message/__manifest__.py
odoo/addons/cms_status_message/i18n/fr.po
odoo/addons/cms_status_message/i18n/it.po
odoo/addons/cms_status_message/images/preview.png
odoo/addons/cms_status_message/models/__init__.py
odoo/addons/cms_status_message/models/website.py
odoo/addons/cms_status_message/static/description/icon.png
odoo/addons/cms_status_message/static/src/js/tool.js
odoo/addons/cms_status_message/templates/assets.xml
odoo/addons/cms_status_message/templates/status_message.xml
odoo/addons/cms_status_message/tests/__init__.py
odoo/addons/cms_status_message/tests/test_message.py
odoo11_addon_cms_status_message-11.0.1.1.0.dist-info/DESCRIPTION.rst
odoo11_addon_cms_status_message-11.0.1.1.0.dist-info/METADATA
odoo11_addon_cms_status_message-11.0.1.1.0.dist-info/RECORD
odoo11_addon_cms_status_message-11.0.1.1.0.dist-info/WHEEL
odoo11_addon_cms_status_message-11.0.1.1.0.dist-info/metadata.json
odoo11_addon_cms_status_message-11.0.1.1.0.dist-info/top_level.txt
